odoo/addons/maintenance_equipment_tags/README.rst
odoo/addons/maintenance_equipment_tags/__init__.py
odoo/addons/maintenance_equipment_tags/__manifest__.py
odoo/addons/maintenance_equipment_tags/i18n/es.po
odoo/addons/maintenance_equipment_tags/i18n/maintenance_equipment_tags.pot
odoo/addons/maintenance_equipment_tags/models/__init__.py
odoo/addons/maintenance_equipment_tags/models/maintenance_equipment.py
odoo/addons/maintenance_equipment_tags/models/maintenance_equipment_tag.py
odoo/addons/maintenance_equipment_tags/readme/CONTRIBUTORS.rst
odoo/addons/maintenance_equipment_tags/readme/DESCRIPTION.rst
odoo/addons/maintenance_equipment_tags/security/ir.model.access.csv
odoo/addons/maintenance_equipment_tags/static/description/icon.png
odoo/addons/maintenance_equipment_tags/static/description/index.html
odoo/addons/maintenance_equipment_tags/views/maintenance_equipment.xml
odoo/addons/maintenance_equipment_tags/views/maintenance_equipment_tag.xml
odoo11_addon_maintenance_equipment_tags-11.0.1.1.0.dist-info/METADATA
odoo11_addon_maintenance_equipment_tags-11.0.1.1.0.dist-info/WHEEL
odoo11_addon_maintenance_equipment_tags-11.0.1.1.0.dist-info/top_level.txt
odoo11_addon_maintenance_equipment_tags-11.0.1.1.0.dist-info/RECORD
